[
    {
        "id": "03_11_20_12_23",
        "name": "wangwang1230__te-empl",
        "rootPath": "/home/mbrito/git/thesis-web-applications/monoliths",
        "relativePath": "wangwang1230__te-empl",
        "clusterString": "{0: ['com.empl.mgr.controller.TrainingController', 'com.empl.mgr.controller.support.AbstractController', 'com.empl.mgr.service.TrainingService', 'com.empl.mgr.service.EmployeesService', 'com.empl.mgr.support.JSONReturn', 'com.empl.mgr.controller.RoleController', 'com.empl.mgr.controller.support.SupportController', 'com.empl.mgr.controller.EmployeesFormalController', 'com.empl.mgr.controller.AccountController', 'com.empl.mgr.controller.ModuleController', 'com.empl.mgr.controller.PositionController', 'com.empl.mgr.controller.EmployeesInternshipController', 'com.empl.mgr.controller.EmployeesDepartureController', 'com.empl.mgr.controller.DepartmentController', 'com.empl.mgr.service.RoleService', 'com.empl.mgr.service.ModuleService', 'com.empl.mgr.service.DepartmentService', 'com.empl.mgr.service.PositionService', 'com.empl.mgr.intercept.SecureValidInterceptor', 'com.empl.mgr.exception.ExceptionIntercept', 'com.empl.mgr.support.RandomValidateCode'], 1: ['com.empl.mgr.service.impl.TrainingServiceImpl', 'com.empl.mgr.dao.TrainingDao', 'com.empl.mgr.dao.TrainingNoteDao', 'com.empl.mgr.dao.EmployeesTrainingLogDao', 'com.empl.mgr.model.TeTraining', 'com.empl.mgr.dto.TrainingListDto', 'com.empl.mgr.model.TeTrainingNote', 'com.empl.mgr.dto.TrainingRecordDto', 'com.empl.mgr.model.TeEmployeesTrainingLog', 'com.empl.mgr.utils.VerifyUtils', 'com.empl.mgr.constant.TrainingState', 'com.empl.mgr.constant.TrainLogState', 'com.empl.mgr.dto.EmployeesTrainingRecordDto'], 2: ['com.empl.mgr.dto.EmployeesInfoDto', 'com.empl.mgr.service.impl.EmployeesServiceImpl', 'com.empl.mgr.dao.EmployeesBasicDao', 'com.empl.mgr.dao.EmployeesDetailDao', 'com.empl.mgr.dao.EmployeesLogDao', 'com.empl.mgr.dao.EmployeesCompanyDao', 'com.empl.mgr.dto.EmployeesAddressDto', 'com.empl.mgr.dto.EmployeesCompnayDto', 'com.empl.mgr.utils.CompareUtil', 'com.empl.mgr.utils.DateTimeUtil', 'com.empl.mgr.intercept.TeMethodIntercept', 'com.empl.mgr.service.impl.EmployeesLogServiceImpl', 'com.empl.mgr.model.TeEmployeesBasic', 'com.empl.mgr.dto.EemplByNoneTrainingLogDto', 'com.empl.mgr.dto.EmployeesInternshipListDto', 'com.empl.mgr.model.TeEmployeesDetail', 'com.empl.mgr.service.EmployeesLogService', 'com.empl.mgr.model.TeEmployeesLog', 'com.empl.mgr.model.TeEmployeesCompany', 'com.empl.mgr.dto.EmployeesBasicInfoDto', 'com.empl.mgr.dto.EmployeesLogDto', 'com.empl.mgr.constant.EmployeesLogType'], 3: ['com.empl.mgr.service.impl.AddressServiceImpl', 'com.empl.mgr.service.AddressService', 'com.empl.mgr.controller.support.AddressController', 'com.empl.mgr.dao.ProvinceDao', 'com.empl.mgr.dao.CityDao', 'com.empl.mgr.dao.CountyDao', 'com.empl.mgr.dao.TownshipDao', 'com.empl.mgr.dao.VillageDao', 'com.empl.mgr.dto.AddressDto', 'com.empl.mgr.dao.support.AbstractDao', 'com.empl.mgr.model.TeProvince', 'com.empl.mgr.model.TeCity', 'com.empl.mgr.model.TeCounty', 'com.empl.mgr.model.TeTownship', 'com.empl.mgr.model.TeVillage', 'com.empl.mgr.dao.AddressDao', 'com.empl.mgr.dao.ChooseNationalDao', 'com.empl.mgr.dao.ChooseEducationDao', 'com.empl.mgr.dao.ChoosePoliticsDao', 'com.empl.mgr.dao.ChooseMarriageDao', 'com.empl.mgr.model.TeAddress', 'com.empl.mgr.model.TeChooseNational', 'com.empl.mgr.model.TeChooseEducation', 'com.empl.mgr.model.TeChoosePolitics', 'com.empl.mgr.model.TeChooseMarriage'], 4: ['com.empl.mgr.service.impl.AccountServiceImpl', 'com.empl.mgr.service.AccountService', 'com.empl.mgr.dao.AccountDao', 'com.empl.mgr.model.TeAccount', 'com.empl.mgr.dto.AccountListDto', 'com.empl.mgr.dto.RoleDto', 'com.empl.mgr.utils.EncryptUtil'], 5: ['com.empl.mgr.service.impl.DepartmentServiceImpl', 'com.empl.mgr.service.impl.PositionServiceImpl', 'com.empl.mgr.dao.PositionDao', 'com.empl.mgr.model.TePosition', 'com.empl.mgr.dto.PositionListDto', 'com.empl.mgr.dto.PositionDto', 'com.empl.mgr.dao.DepartmentDao', 'com.empl.mgr.utils.PageUtils', 'com.empl.mgr.dto.PageDto', 'com.empl.mgr.model.TeDepartment', 'com.empl.mgr.dto.DepartmentSelectDto', 'com.empl.mgr.dto.DepartmentListDto', 'com.empl.mgr.dto.SelectDto'], 6: ['com.empl.mgr.service.impl.RoleServiceImpl', 'com.empl.mgr.service.impl.ModuleServiceImpl', 'com.empl.mgr.dao.RoleDao', 'com.empl.mgr.dao.AccountRoleDao', 'com.empl.mgr.dao.ModuleDao', 'com.empl.mgr.dao.RoleModuleDao', 'com.empl.mgr.model.TeRole', 'com.empl.mgr.model.TeAccountRole', 'com.empl.mgr.dto.RoleListDto', 'com.empl.mgr.model.TeModule', 'com.empl.mgr.utils.SupportUtil', 'com.empl.mgr.model.TeRoleModule', 'com.empl.mgr.dto.ModuleDto'], 7: ['com.empl.mgr.service.impl.RoleModuleServiceImpl', 'com.empl.mgr.service.RoleModuleService']}",
        "commitHash": "",
        "Modularity": 0.6027403948842064
    }
]